setup.cfg
setup.py
ActionML.egg-info/PKG-INFO
ActionML.egg-info/SOURCES.txt
ActionML.egg-info/dependency_links.txt
ActionML.egg-info/requires.txt
ActionML.egg-info/top_level.txt
actionml/__init__.py
actionml/connection.py