Metadata-Version: 1.1
Name: ActionML
Version: 0.0.6
Summary: ActionML Python SDK
Home-page: http://actionml.com
Author: The ActionML Team
Author-email: support@actionml.com
License: LICENSE.txt
Platform: UNKNOWN
Classifier: Programming Language :: Python
Classifier: License :: OSI Approved :: Apache Software License
Classifier: Operating System :: OS Independent
Classifier: Development Status :: 4 - Beta
Classifier: Intended Audience :: Developers
Classifier: Intended Audience :: Science/Research
Classifier: Environment :: Web Environment
Classifier: Topic :: Internet :: WWW/HTTP
Classifier: Topic :: Scientific/Engineering :: Artificial Intelligence
Classifier: Topic :: Scientific/Engineering :: Information Analysis
Classifier: Topic :: Software Development :: Libraries :: Python Modules
